algoesup/__init__.py
algoesup/magics.py
algoesup/test.py
algoesup/time.py
algoesup-0.4.2.dist-info/LICENSE
algoesup-0.4.2.dist-info/METADATA
algoesup-0.4.2.dist-info/WHEEL
algoesup-0.4.2.dist-info/RECORD
