Metadata-Version: 2.3
Name: algoesup
Version: 0.4.2
Summary: Algorithmic essay support library
License: BSD-3-Clause
Keywords: education
Author: Michel Wermelinger
Author-email: michel.wermelinger@open.ac.uk
Requires-Python: >=3.10,<4.0
Classifier: Intended Audience :: Education
Classifier: License :: OSI Approved :: BSD License
Classifier: Operating System :: OS Independent
Classifier: Programming Language :: Python :: 3
Classifier: Programming Language :: Python :: 3.10
Classifier: Programming Language :: Python :: 3.11
Classifier: Programming Language :: Python :: 3.12
Classifier: Programming Language :: Python :: 3.13
Classifier: Topic :: Education
Requires-Dist: ipython (>=8.13.1,<9.0.0)
Requires-Dist: matplotlib (>=3.4.2,<4.0.0)
Project-URL: Changelog, https://github.com/dsa-ou/algoesup/blob/main/CHANGELOG.md
Project-URL: Documentation, https://dsa-ou.github.io/algoesup/library/
Project-URL: Repository, https://github.com/dsa-ou/algoesup/
